logician/__init__.py
logician/formatters.py
logician/logician.py
logician/time_aware.py
logician/types.py
logician-0.3.4.dist-info/LICENSE
logician-0.3.4.dist-info/METADATA
logician-0.3.4.dist-info/WHEEL
logician-0.3.4.dist-info/RECORD
