Metadata-Version: 2.3
Name: logician
Version: 0.3.4
Summary: The logical choice for Python logging
License: LGPL-3.0-or-later
Author: Danny Stewart
Author-email: danny@stewart.cc
Requires-Python: >=3.12
Classifier: Development Status :: 5 - Production/Stable
Classifier: Intended Audience :: Developers
Classifier: License :: OSI Approved :: GNU Lesser General Public License v3 or later (LGPLv3+)
Classifier: Programming Language :: Python :: 3
Classifier: Programming Language :: Python :: 3.12
Classifier: Programming Language :: Python :: 3.13
Classifier: Topic :: System :: Logging
Requires-Dist: polykit (>=0.1.1)
